bugyi/release_tools/__init__.py
bugyi/release_tools/cli.py
bugyi.release_tools-0.1.0.data/scripts/README.md
bugyi.release_tools-0.1.0.dist-info/METADATA
bugyi.release_tools-0.1.0.dist-info/WHEEL
bugyi.release_tools-0.1.0.dist-info/entry_points.txt
bugyi.release_tools-0.1.0.dist-info/top_level.txt
bugyi.release_tools-0.1.0.dist-info/RECORD
